synapsegraph_lib/__init__.py
synapsegraph_lib/audit/__init__.py
synapsegraph_lib/audit/audit_logger.py
synapsegraph_lib/core/__init__.py
synapsegraph_lib/core/config.py
synapsegraph_lib/core/database.py
synapsegraph_lib/core/models.py
synapsegraph_lib/core/retrieval.py
synapsegraph_lib/core/synapse_graph.py
synapsegraph_lib/explainability/belief_change_explainer.py
synapsegraph_lib/extraction/__init__.py
synapsegraph_lib/extraction/extractor.py
synapsegraph_lib/ingestion/__init__.py
synapsegraph_lib/ingestion/ingestor.py
synapsegraph_lib/integrity/__init__.py
synapsegraph_lib/integrity/balance_monitoring.py
synapsegraph_lib/integrity/conflict_resolution.py
synapsegraph_lib/integrity/conflict_resolution_llm.py
synapsegraph_lib/scalability/__init__.py
synapsegraph_lib/scalability/caching.py
synapsegraph_lib/scalability/summarization.py
synapsegraph_lib/synthesis/__init__.py
synapsegraph_lib/synthesis/belief_clustering.py
synapsegraph_lib/synthesis/belief_manager.py
synapsegraph_lib/synthesis/opinion_formation.py
synapsegraph_lib/temporal/__init__.py
synapsegraph_lib/temporal/temporal_management.py
synapsegraph_lib/utils/__init__.py
synapsegraph_lib/utils/entity_resolution.py
synapsegraph_lib/utils/helpers.py
synapsegraph_lib/utils/text_processor.py
synapsegraph_lib/utils/visualization.py
synapsegraph_lib-0.1.1.dist-info/LICENSE
synapsegraph_lib-0.1.1.dist-info/METADATA
synapsegraph_lib-0.1.1.dist-info/WHEEL
synapsegraph_lib-0.1.1.dist-info/entry_points.txt
synapsegraph_lib-0.1.1.dist-info/RECORD
