Metadata-Version: 2.3
Name: synapsegraph-lib
Version: 0.1.1
Summary: SynapseGraph is a real-time, self-updating knowledge graph designed to integrate with LLMs, enabling intelligent belief formation, probabilistic knowledge updates, and scalable memory management. It continuously learns, refines, and evolves its understanding—mimicking human cognition.
License: MIT
Keywords: knowledge graph,ai,temporal,beliefs,neo4j
Author: Jack Nam
Author-email: naminalstack+synapse@gmail.com
Requires-Python: >=3.9,<4.0
Classifier: Development Status :: 3 - Alpha
Classifier: Intended Audience :: Developers
Classifier: License :: OSI Approved :: MIT License
Classifier: Programming Language :: Python :: 3
Classifier: Programming Language :: Python :: 3.9
Classifier: Programming Language :: Python :: 3.10
Classifier: Programming Language :: Python :: 3.11
Classifier: Programming Language :: Python :: 3.12
Classifier: Programming Language :: Python :: 3.13
Classifier: Topic :: Software Development :: Libraries :: Python Modules
Requires-Dist: langchain (>=0.3.20,<0.4.0)
Requires-Dist: langchain-community (>=0.3.19,<0.4.0)
Requires-Dist: langchain-openai (>=0.3.8,<0.4.0)
Requires-Dist: neo4j (>=5.28.1,<6.0.0)
Requires-Dist: openai (>=1.65.5,<2.0.0)
Requires-Dist: pydantic (>=2.0.0)
Requires-Dist: python-dotenv (>=1.0.1,<2.0.0)
Requires-Dist: python-levenshtein (>=0.27.1,<0.28.0)
Requires-Dist: scikit-learn (>=1.6.1,<2.0.0)
Requires-Dist: sentence-transformers (>=3.4.1,<4.0.0)
Project-URL: Repository, https://github.com/thienlnam/SynapseGraph
